Metadata-Version: 2.1
Name: tvpdownloader
Version: 0.5.0
Summary: Download episodes from vod.tvp.pl
Home-page: https://github.com/patkub/tvpdownloader
Author: Patrick Kubiak
Author-email: pk9948@rit.edu
License: UNKNOWN
Platform: UNKNOWN
Classifier: Programming Language :: Python :: 3
Classifier: License :: OSI Approved :: MIT License
Classifier: Operating System :: OS Independent
